django_fixtures/__init__.py
django_fixtures/dataset.py
django_fixtures/decorators.py
django_fixtures/exceptions.py
django_fixtures/fixtures.py
django_fixtures/unittests.py
django_fixtures/utilities.py
django_fixtures/management/commands/createfixtures.py
django_fixtures_rx-0.2.3.dist-info/LICENSE
django_fixtures_rx-0.2.3.dist-info/METADATA
django_fixtures_rx-0.2.3.dist-info/WHEEL
django_fixtures_rx-0.2.3.dist-info/top_level.txt
django_fixtures_rx-0.2.3.dist-info/RECORD
