Metadata-Version: 2.1
Name: django-fixtures-rx
Version: 0.2.3
Summary: Advanced django fixtures.
Home-page: https://github.com/retxxxirt/django-fixtures
Author: retxxxirt
Author-email: retxxirt@gmail.com
License: MIT
Keywords: django,django fixtures,django-fixtures,fixtures,tests,unittests
Platform: UNKNOWN
Requires-Dist: wheel
